Metadata-Version: 2.1
Name: aiohttp-ip-rotator
Version: 1.0
Summary: Change the IP address with each http request using the AWS API Gateway.
Home-page: https://github.com/D4rkwat3r/aiohttp-ip-rotator
Author-email: ktoya170214@gmail.com
License: UNKNOWN
Platform: UNKNOWN
